neatbio2/.DS_Store
neatbio2/__init__.py
neatbio2/neatbio2.py
neatbio2/sequtils/__init__.py
neatbio2/sequtils/sequtils.py
neatbio2-0.1.0.dist-info/METADATA
neatbio2-0.1.0.dist-info/WHEEL
neatbio2-0.1.0.dist-info/RECORD
